[
    { "id": 1, "tr": "Ali okulda.", "en": "Ali is at the school." },
    { "id": 2, "tr": "Sen okulda mısın?", "en": "Are you at the school?" },
    { "id": 3, "tr": "Sen okulda değil misin?", "en": "Aren't you at the school?" },
    { "id": 4, "tr": "Sen niçin okulda değilsin?", "en": "Why aren't you at the school?" },
    { "id": 5, "tr": "Çocuklar bizimle beraber.", "en": "The children are with us." },
    { "id": 6, "tr": "Biz çocuklarla beraber değiliz.", "en": "We aren't with the children." },
    { "id": 7, "tr": "Siz çocuklarla beraber misiniz?", "en": "Are you with the children?" },
    { "id": 8, "tr": "Çocuklar sizinle beraber mi?", "en": "Are the children with you?" },
    { "id": 9, "tr": "Pazar günü Antalya’dayız.", "en": "We are in Antalya on Sunday." },
    { "id": 10, "tr": "Pazartesi günü burada değiller.", "en": "They aren't here on Monday." },
    { "id": 11, "tr": "Salı günü bizimle beraber Ankara'dalar.", "en": "They are in Ankara with us on Tuesday." },
    { "id": 12, "tr": "Onlar niçin bizimle beraber?", "en": "Why are they with us?" },
    { "id": 13, "tr": "Çocuklar evde.", "en": "The children are at home." },
    { "id": 14, "tr": "Çocuklar bahçede değil.", "en": "The children aren't in the garden." },
    { "id": 15, "tr": "Çocuklar okulda mı?", "en": "Are the children at the school?" },
    { "id": 16, "tr": "Çocuklar saat kaçta okulda?", "en": "What time are the children at the school?" },
    { "id": 17, "tr": "Çocuklar ne zaman okulda?", "en": "When are the children at the school?" },
    { "id": 18, "tr": "Okul için otobüsteyim.", "en": "I'm on the bus for the school." },
    { "id": 19, "tr": "Okuldan arkadaşlarımla beraber bir kafedeyim.", "en": "I'm in a cafe with my friends from the school." },
    { "id": 20, "tr": "Okuldan sonra sizinleyim.", "en": "I'm with you after the school." },
    { "id": 21, "tr": "Kıştan önce burada değilim.", "en": "I'm not here before the winter." },
    { "id": 22, "tr": "Yazdan sonra burada mısın?", "en": "Are you here after the summer?" },
    { "id": 23, "tr": "Sizin için buradayım.", "en": "I'm here for you." },
    { "id": 24, "tr": "Kim burada?", "en": "Who is here?" },
    { "id": 25, "tr": "Kim sizin için burada?", "en": "Who is here for you?" },
    { "id": 26, "tr": "Onlar senin için burada mı?", "en": "Are they here for you?" },
    { "id": 27, "tr": "Onlar neden senin için burada?", "en": "Why are they here for you?" },
    { "id": 28, "tr": "Bu para, ailen için.", "en": "This money is for your family." },
    { "id": 29, "tr": "Bu kitaplar, çocuklarımız için.", "en": "These books are for our children." },
    { "id": 30, "tr": "Ocaktaki yemek, ailem için.", "en": "The food on the stove is for my family." },
    { "id": 31, "tr": "Niçin buradasın?", "en": "Why are you here?" },
    { "id": 32, "tr": "Ne zaman oradalar?", "en": "When are they there?" },
    { "id": 33, "tr": "Nasıllar?", "en": "How are they?" },
    { "id": 34, "tr": "Hava nasıl?", "en": "How is the weather?" },
    { "id": 35, "tr": "Saat kaç?", "en": "What time is it?" },
    { "id": 36, "tr": "Kaç yaşındasın?", "en": "How old are you?" },
    { "id": 37, "tr": "Neredeler?", "en": "Where are they?" },
    { "id": 38, "tr": "Telefonum nerede?", "en": "Where is my phone?" },
    { "id": 39, "tr": "Çocukların nasıl?", "en": "How are your children?" },
    { "id": 40, "tr": "Okulun saat kaçta?", "en": "What time is your school?" },
    { "id": 41, "tr": "Uçağımız saat kaçta?", "en": "What time is our flight?" },
    { "id": 42, "tr": "Hangisi benim bilgisayarım?", "en": "Which one is my computer?" },
    { "id": 43, "tr": "Hangi bilgisayar benim?", "en": "Which computer is mine?" },
    { "id": 44, "tr": "Bu, kimin evi?", "en": "Whose house is this?" },
    { "id": 45, "tr": "Bu, kimin parası?", "en": "Whose money is this?" },
    { "id": 46, "tr": "Bu para, kimin?", "en": "Whose is this money?" },
    { "id": 47, "tr": "Arkadaşlarımla beraber ofisteyim.", "en": "I'm in the office with my friends." },
    { "id": 48, "tr": "Arkadaşlarım olmadan ofisteyim.", "en": "I'm in the office without my friends." },
    { "id": 49, "tr": "Ayşe arkadaşlarıyla beraber ofiste değil.", "en": "Ayşe isn't in the office with her friends." },
    { "id": 50, "tr": "Sen arkadaşlarınla beraber ofiste misin?", "en": "Are you in the office with your friends?" },
    { "id": 51, "tr": "Evdeyim.", "en": "I'm at home." },
    { "id": 52, "tr": "Ailemle beraber evdeyim.", "en": "I'm at home with my family." },
    { "id": 53, "tr": "Sabahleyin saat dokuzda ailemle beraber evdeyim.", "en": "I'm at home with my family at nine o'clock in the morning." },
    { "id": 54, "tr": "Ali okulda değil.", "en": "Ali isn't at the school." },
    { "id": 55, "tr": "Ali bugün okulda değil.", "en": "Ali isn't at the school today." },
    { "id": 56, "tr": "Ali evdeki sorunlar yüzünden bugün okulda değil.", "en": "Ali isn't at the school today because of the problems at home." },
    { "id": 57, "tr": "Orada mısın?", "en": "Are you there?" },
    { "id": 58, "tr": "Okuldan sonra orada mısın?", "en": "Are you there after the school?" },
    { "id": 59, "tr": "Okuldan sonra arkadaşlarınla beraber orada mısın?", "en": "Are you there with your friends after the school?" },
    { "id": 60, "tr": "Niçin okuldan sonra arkadaşlarınla beraber oradasın?", "en": "Why are you there with your friends after the school?" },
    { "id": 61, "tr": "Okuldan sonra arkadaşlarınla beraber neredesin?", "en": "Where are you with your friends after the school?" },
    { "id": 62, "tr": "Annem tatilde.", "en": "My mother is on holiday." },
    { "id": 63, "tr": "Annem üniversiteden arkadaşlarıyla beraber tatilde.", "en": "My mother is on holiday with her friends from the  university." },
    { "id": 64, "tr": "Annem bu yaz üniversiteden arkadaşlarıyla beraber Bodrum'da tatilde.", "en": "My mother is on holiday in Bodrum with her friends from the university this summer." },
    { "id": 65, "tr": "Annem tatilde.", "en": "My mother is on holiday." },
    { "id": 66, "tr": "Annem tatilde mi?", "en": "Is my mother on holiday?" },
    { "id": 67, "tr": "Annem niçin tatilde?", "en": "Why is my mother on holiday?" },
    { "id": 68, "tr": "Annem nerede tatilde?", "en": "Where is my mother on holiday?" },
    { "id": 69, "tr": "Bu süt, bahçedeki kediler için.", "en": "This milk is for the cats in the garden." },
    { "id": 70, "tr": "Bu süt, bahçedeki kediler için değil.", "en": "This milk isn't for the cats in the garden." },
    { "id": 71, "tr": "Bu süt bahçede kediler için mi?", "en": "Is this milk for the cats in the garden?" },
    { "id": 72, "tr": "Bu süt bahçedeki kediler için değil mi?", "en": "Isn't this milk for the cats in the garden?" },
    { "id": 73, "tr": "Bahçedeki kediler nerede?", "en": "Where are the cats in the garden?" },
    { "id": 74, "tr": "Bahçedeki kediler nasıl?", "en": "How are the cats in the garden?" },
    { "id": 75, "tr": "Bahçedeki kediler kaç yaşında?", "en": "How old are the cats in the garden?" },
    { "id": 76, "tr": "Denizdeki gemiler eski.", "en": "The ships on the sea are old." },
    { "id": 77, "tr": "Denizdeki gemiler hızlı değil.", "en": "The ships on the sea aren't fast." },
    { "id": 78, "tr": "Denizdeki gemiler hızlı mı?", "en": "Are the ships on the sea fast?" },
    { "id": 79, "tr": "Denizdeki gemiler ne kadar hızlı?", "en": "How fast are the ships on the sea?" },
    { "id": 80, "tr": "Denizdeki gemiler nasıl?", "en": "How are the ships on the sea?" },
    { "id": 81, "tr": "Denizdeki gemiler nerede?", "en": "Where are the ships on the sea?" },
    { "id": 82, "tr": "Türkiye'deki insanlar yorgun.", "en": "The people in Turkey are tired." },
    { "id": 83, "tr": "Türkiye'deki insanlar mutlu mu?", "en": "Are the people in Turkey happy?" },
    { "id": 84, "tr": "Türkiye'deki insanlar mutlu değil.", "en": "The people in Turkey aren't happy." },
    { "id": 85, "tr": "Türkiye'deki insanlar niçin mutlu değil?", "en": "Why aren't the people in Turkey happy?" },
    { "id": 86, "tr": "Tatildeyiz.", "en": "We are on holiday." },
    { "id": 87, "tr": "Bodrum'da tatildeyiz.", "en": "We are on holiday in Bodrum." },
    { "id": 88, "tr": "Ailemle beraber Bodrum’da tatildeyiz.", "en": "We are on holiday in Bodrum with my family." },
    { "id": 89, "tr": "Bu yaz ailemle beraber Bodrum'da tatildeyiz.", "en": "We are on holiday in Bodrum with my family this summer." },
    { "id": 90, "tr": "Ayşe Ankara'da.", "en": "Ayşe is in Ankara." },
    { "id": 91, "tr": "Ayşe kışın Ankara'da.", "en": "Ayşe is in Ankara in the winter." },
    { "id": 92, "tr": "Ayşe kışın ailesiyle beraber Ankara'da.", "en": "Ayşe is in Ankara with her family in the winter." },
    { "id": 93, "tr": "Ayşe kışın şubat ayında ailesiyle beraber Ankara'da.", "en": "Ayşe is in Ankara with her family in February in the winter." },
    { "id": 94, "tr": "Bu film, bizim hakkımızda.", "en": "This film is about us." },
    { "id": 95, "tr": "Bu film, Türkiye hakkında.", "en": "This film is about Turkey." },
    { "id": 96, "tr": "Bu film, Türkiye'nin sorunları hakkında.", "en": "This film is about the problems of Turkey." },
    { "id": 97, "tr": "Bu film, Türkiye'nin sorunlarının çözümü hakkında.", "en": "This film is about the solution to the problems of Turkey." },
    { "id": 98, "tr": "Evimdeyim.", "en": "I'm in my house." },
    { "id": 99, "tr": "Evimde salondayım.", "en": "I'm in the living room in my house." },
    { "id": 100, "tr": "Evimde oğlumla beraber salondayım.", "en": "I'm in the living room with my son in my house." },
    { "id": 101, "tr": "Oğlum benimle beraber salonda.", "en": "My son is in the living room with me." },
    { "id": 102, "tr": "Okuldan önce oğlum benimle beraber salonda.", "en": "My son is in the living room with me before the school." },
    { "id": 103, "tr": "İşten önce ailemle beraber mutfaktayım.", "en": "I'm in the kitchen with my family before work." },
    { "id": 104, "tr": "Bu kitaplar, sizin için.", "en": "These books are for you." },
    { "id": 105, "tr": "Bu kitaplar, sizin hakkınızda.", "en": "These books are about you." },
    { "id": 106, "tr": "Elimdeki kitaplar, sizin için.", "en": "The books in my hand are for you." },
    { "id": 107, "tr": "Masanın üstündeki para benim için.", "en": "The money on the table is for me." },
    { "id": 108, "tr": "Elimdeki para senin için.", "en": "The money in my hand is for you." },
    { "id": 109, "tr": "Okuldan önce arkadaşlarımla beraber sınıftayım.", "en": "I'm in the classroom with my friends before the school." },
    { "id": 110, "tr": "Ali okuldan sonra arkadaşlarıyla beraber bir kafede.", "en": "Ali is in a cafe with his friends after the school." },
    { "id": 111, "tr": "Ayşe öğlenleyin iş yerinden arkadaşlarıyla beraber bir restoranda.", "en": "Ayşe is in a restaurant with her friends from work at noon." },
    { "id": 112, "tr": "Ben ailem olmadan Ankara'dayım.", "en": "I'm in Ankara without my family." },
    { "id": 113, "tr": "Kitaptaki hikayeler ilginç.", "en": "The stories in the book are interesting." },
    { "id": 114, "tr": "Kitaptaki hikayeler komik değil.", "en": "The stories in the book aren't funny." },
    { "id": 115, "tr": "Kitaptaki hikayeler ilginç mi?", "en": "Are the stories in the book interesting?" },
    { "id": 116, "tr": "Kitaptaki hikayeler komik mi?", "en": "Are the stories in the book funny?" },
    { "id": 117, "tr": "Kitaptaki hikayeler nasıl?", "en": "How are the stories in the book?" },
    { "id": 118, "tr": "Ayşe işten sonra kızıyla beraber mutfakta.", "en": "Ayşe is in the kitchen with her daughter after work." },
    { "id": 119, "tr": "Kızım okuldan önce benimle beraber mutfakta.", "en": "My daughter is in the kitchen with me before the school." },
    { "id": 120, "tr": "Oğlum yağmurdan sonra kedilerle beraber bahçede.", "en": "My son is in the garden with the cats after the rain." },
    { "id": 121, "tr": "Kedim öğleden sonra çocuklarımla beraber koltukta.", "en": "My cat is on the sofa with my children in the afternoon." },
    { "id": 122, "tr": "Pazartesi akşamı arkadaşlarımla beraber küçük bir restorandayım.", "en": "I'm in a small restaurant with my friends on Monday evening." },
    { "id": 123, "tr": "Salı öğleden sonra iş yerinden arkadaşlarımla beraber ofisteyim.", "en": "I'm in the office with my friends from work on Tuesday afternoon." },
    { "id": 124, "tr": "Çarşamba akşamı amcamla beraber köydeki bahçedeyim.", "en": "I'm in the garden in the village with my uncle on Wednesday evening." },
    { "id": 125, "tr": "Hafta sonu ailemle beraber köydeyim.", "en": "I'm in the village with my family at the weekend." },
    { "id": 126, "tr": "Ali ayın sonunda çocuklarıyla beraber tatilde.", "en": "Ali is on holiday with his children at the end of the month." },
    { "id": 127, "tr": "Bir restorandayım.", "en": "I'm in a restaurant." },
    { "id": 128, "tr": "İş yerinden arkadaşlarımla beraber bir restorandayım.", "en": "I'm in a restaurant with my friends from work." },
    { "id": 129, "tr": "Uzun bir günün ardından iş yerinden arkadaşlarımla beraber bir restorandayım.", "en": "I'm in a restaurant with my friends from work after a long day." },
    { "id": 130, "tr": "Ayın sonunda çocuklarımla beraber tatil için babamın köyündeyiz.", "en": "We're in my father's village for holiday with my children at the end of the month." },
    { "id": 131, "tr": "Ali yazın başında bir toplantı için iş yerinden arkadaşlarıyla beraber Antalya'da bir otelde.", "en": "Ali is in a hotel in Antalya with his friends from work for a meeting at the beginning of summer." },
    { "id": 132, "tr": "Ayşe elinde iki bardak suyla sandalyenin yanında.", "en": "Ayşe is at the chair with two glasses of water in her hand." },
    { "id": 133, "tr": "Muhammed yazın ağustos ayında ailesiyle beraber güzel bir tatil için Bodrum’da.", "en": "Muhammed is in Bodrum for a nice holiday with his family in August in the summer." }
  ]
